{
  "slug": "sumeru",
  "name": "Sumeru Equity Partners",
  "website": "https://sumerupartners.com",
  "hq": "Foster City, CA",
  "overview": "Bay Area-based tech-focused growth and buyout firm. Originated as a spinout from Silver Lake's growth strategy; primarily targets software and tech-enabled services in the middle market.",
  "sectorFocus": ["software", "tech-enabled services", "internet"],
  "notable": [],
  "bdNotes": "Geographically convenient for a Mill Valley-based candidate. Confirm current org and BD-team composition via refresh before reaching out."
}
